{
  "posts": [
    {
      "id": "1",
      "name": "Jersey Cow",
      "image": "https://i.pinimg.com/originals/32/f5/44/32f544d9bfc81ef877e3d10b53d2cb41.jpg",
      "milk": "15 liter per day",
      "state": "Pregnancy",
      "price": "40000",
      "extra": "And more details contact us 9486666928"
    },
    {
      "id": "2",
      "name": "Jersey Cow",
      "image": "https://i.pinimg.com/originals/16/dd/b4/16ddb416e38a0eaecd4d9661a8ba5d15.jpg",
      "milk": "13 liter per day",
      "state": "Milk Cattle",
      "price": "38000",
      "extra": "And more details contact us 9486666928"
    },
    {
      "id": "3",
      "name": "Jersey Cow",
      "image": "https://images.fineartamerica.com/images-medium-large-5/jersey-cow-in-pasture-michelle-wrighton.jpg",
      "milk": "14 liter per day",
      "state": "Milk Cattle",
      "price": "37000",
      "extra": "And more details contact us 9486666928"
    },
    {
      "id": "4",
      "name": "Helstein Frienian Cow",
      "image": "https://tiimg.tistatic.com/fp/1/005/578/holstein-friesian-cow-440.jpg",
      "milk": "10 liter per day",
      "state": "Pregnancy",
      "price": "30000",
      "extra": "And more details contact us 9486666928"
    },
    {
      "id": "5",
      "name": "Helstein Frienian Cow",
      "image": "https://i.pinimg.com/736x/f0/64/fc/f064fc0ec9b59f09ef71a98bf3dec55e--cattle-farming-holstein-cows.jpg",
      "milk": "12 liter per day",
      "state": "Milk Cattle + Calf",
      "price": "38000",
      "extra": "And more details contact us 9486666928"
    },
    {
      "id": "6",
      "name": "Helstein Frienian Cow",
      "image": "https://images.engormix.com/profile_photos/ph-20180216_061647-S-12368-hols.jpg",
      "milk": "18 liter per day",
      "state": "Milk Cattle",
      "price": "50000",
      "extra": "And more details contact us 9486666928"
    },
    {
      "firstname": "akila",
      "lastname": "c",
      "id": "vhHeBnJ"
    },
    {
      "firstname": "akila",
      "lastname": "c",
      "id": "p0R4E-d"
    },
    {
      "firstname": "cbkgcvkgvfuohdfub",
      "lastname": "akoj;vjlfhvjvjcbv",
      "id": "np3qWHD"
    }
  ],
  "products": [
    {
      "name": "jillu",
      "mobile": 12378965418,
      "address": "maruthaniyoor",
      "id": 1
    },
    {
      "name": "pavi",
      "mobile": 14325446587,
      "address": "avr",
      "id": 2
    }
  ]
}